nodebackup/__init__.py
nodebackup/cloudutils.py
nodebackup/configutils.py
nodebackup/daemon.py
nodebackup/inotifyutils.py
nodebackup/nodebackup.py
nodebackup/stophandler.py
lndnodebackup-0.0.2.dist-info/LICENSE
lndnodebackup-0.0.2.dist-info/METADATA
lndnodebackup-0.0.2.dist-info/WHEEL
lndnodebackup-0.0.2.dist-info/entry_points.txt
lndnodebackup-0.0.2.dist-info/top_level.txt
lndnodebackup-0.0.2.dist-info/zip-safe
lndnodebackup-0.0.2.dist-info/RECORD
